topsis_himani/__init__.py
topsis_himani/topsis.py
topsis_himani_102303648-1.0.2.dist-info/licenses/LICENSE
topsis_himani_102303648-1.0.2.dist-info/METADATA
topsis_himani_102303648-1.0.2.dist-info/WHEEL
topsis_himani_102303648-1.0.2.dist-info/entry_points.txt
topsis_himani_102303648-1.0.2.dist-info/top_level.txt
topsis_himani_102303648-1.0.2.dist-info/RECORD
