Metadata-Version: 2.4
Name: topsis-himani-102303648
Version: 1.0.2
Summary: TOPSIS implementation as a command line tool
Author: Himani Mahajan
Author-email: 
License-File: LICENSE
Requires-Dist: pandas
Requires-Dist: numpy
Dynamic: author
Dynamic: description
Dynamic: description-content-type
Dynamic: license-file
Dynamic: requires-dist
Dynamic: summary
